MyQRPackage/__init__.py
MyQRPackage/QRDecomposition/__init__.py
MyQRPackage/QRDecomposition/household.py
MyQRPackage/QRDecomposition/qr_decomposition.py
MyQRPackage/tests/__init__.py
MyQRPackage/tests/test_household.py
MyQRPackage/tests/test_qr_decomposition.py
MyQRPackage-0.1.dist-info/METADATA
MyQRPackage-0.1.dist-info/WHEEL
MyQRPackage-0.1.dist-info/top_level.txt
MyQRPackage-0.1.dist-info/RECORD
